{
  "$schema": "https://developer.microsoft.com/json-schemas/spfx-build/package-solution.schema.json",
  "solution": {
    "name": "app-customizer-client-side-solution",
    "id": "071c10f6-062b-4012-a1e8-8e1bf2647bce",
    "version": "1.0.0.0",
    "includeClientSideAssets": true,
    "isDomainIsolated": false,
    "features": [
      {
        "title": "Application Extension - Deployment of custom action.",
        "description": "Deploys a custom action with ClientSideComponentId association",
        "id": "57aa6179-aebd-4f56-8344-84bee1ef9182",
        "version": "1.0.0.0",
        "assets": {
          "elementManifests": [
            "elements.xml",
            "clientsideinstance.xml"
          ]
        }
      }
    ]
  },
  "paths": {
    "zippedPackage": "solution/app-customizer.sppkg"
  }
}
